gammarers/aws_codeconnections_host_custom_resource/__init__.py
gammarers/aws_codeconnections_host_custom_resource/py.typed
gammarers/aws_codeconnections_host_custom_resource/_jsii/__init__.py
gammarers/aws_codeconnections_host_custom_resource/_jsii/aws-codeconnections-host-custom-resource@0.8.18.jsii.tgz
gammarers_aws_codeconnections_host_custom_resource-0.8.18.dist-info/LICENSE
gammarers_aws_codeconnections_host_custom_resource-0.8.18.dist-info/METADATA
gammarers_aws_codeconnections_host_custom_resource-0.8.18.dist-info/WHEEL
gammarers_aws_codeconnections_host_custom_resource-0.8.18.dist-info/top_level.txt
gammarers_aws_codeconnections_host_custom_resource-0.8.18.dist-info/RECORD
